coincity/main.py
coincity-0.1.0.dist-info/licenses/LICENSE
coincity-0.1.0.dist-info/METADATA
coincity-0.1.0.dist-info/WHEEL
coincity-0.1.0.dist-info/entry_points.txt
coincity-0.1.0.dist-info/top_level.txt
coincity-0.1.0.dist-info/RECORD
