Metadata-Version: 2.4
Name: coincity
Version: 0.1.0
Summary: Official Client for Coin City!
Author: Viren Sahti
License: License & Disclaimer
Requires-Python: >=3.9
License-File: LICENSE
Requires-Dist: asyncio
Dynamic: license-file
